mircato_stats/__init__.py
mircato_stats/configs/__init__.py
mircato_stats/configs/logging.py
mircato_stats/configs/models.py
mircato_stats/configs/statistics.py
mircato_stats/dicom/__init__.py
mircato_stats/dicom/dicom_folder.py
mircato_stats/models/__init__.py
mircato_stats/models/xgboost.json
mircato_stats/statistics/__init__.py
mircato_stats/statistics/aorta.py
mircato_stats/statistics/body_and_tissues.py
mircato_stats/statistics/centerline.py
mircato_stats/statistics/contrast_detection.py
mircato_stats/statistics/cpr.py
mircato_stats/statistics/nifti.py
mircato_stats/statistics/total.py
mircato_stats/statistics/utils.py
mircato_stats-0.2.3.dist-info/METADATA
mircato_stats-0.2.3.dist-info/WHEEL
mircato_stats-0.2.3.dist-info/entry_points.txt
mircato_stats-0.2.3.dist-info/RECORD
