Metadata-Version: 2.3
Name: mircato-stats
Version: 0.2.3
Summary: Statistics only version of MirCATo for CT image analysis. Much smaller build without torch.
Requires-Python: <3.12,>=3.10
Requires-Dist: cloud-files==4.24.2
Requires-Dist: cloud-volume==8.33.0
Requires-Dist: dicom2nifti>=2.4.11
Requires-Dist: kimimaro==4.0.0
Requires-Dist: loguru>=0.7.2
Requires-Dist: nibabel>=5.2.1
Requires-Dist: numpy==1.26
Requires-Dist: pydicom==2.4.4
Requires-Dist: scikit-image==0.23.2
Requires-Dist: scikit-learn>=1.5.2
Requires-Dist: scipy==1.13.1
Requires-Dist: simpleitk==2.3.1
Requires-Dist: threadpoolctl>=3.5.0
Requires-Dist: xgboost==2.1.0
